Metadata-Version: 2.1
Name: selfcheckgpt
Version: 0.1.6
Summary: SelfCheckGPT: Assessing text-based responses from LLMs
Home-page: https://github.com/potsawee/selfcheckgpt
Author: Potsawee Manakul
Author-email: m.potsawee@gmail.com
License: MIT
Keywords: selfcheckgpt
Platform: UNKNOWN
Classifier: Intended Audience :: Developers
Classifier: Intended Audience :: Science/Research
Classifier: Topic :: Scientific/Engineering :: Artificial Intelligence
Classifier: License :: OSI Approved :: MIT License
Classifier: Programming Language :: Python :: 3
License-File: LICENSE
